asf_theme/__init__.py
asf_theme/main.html
asf_theme/mkdocs_theme.yml
asf_theme/assets/images/ASFLogo-Blue2.png
asf_theme/assets/images/asf-logo-blue-nav.png
asf_theme/assets/images/favicon.ico
asf_theme/assets/images/map.png
asf_theme/assets/javascripts/expert-rec-search.js
asf_theme/assets/stylesheets/asf.css
asf_theme/partials/copyright.html
asf_theme/partials/footer.html
asf_theme/partials/header.html
asf_theme/partials/main.html
asf_theme/partials/search.html
asf_theme/partials/social.html
mkdocs_asf_theme-0.4.0.dist-info/LICENSE
mkdocs_asf_theme-0.4.0.dist-info/METADATA
mkdocs_asf_theme-0.4.0.dist-info/WHEEL
mkdocs_asf_theme-0.4.0.dist-info/entry_points.txt
mkdocs_asf_theme-0.4.0.dist-info/top_level.txt
mkdocs_asf_theme-0.4.0.dist-info/RECORD
