Metadata-Version: 2.1
Name: mkdocs-asf-theme
Version: 0.4.0
Summary: An extension of the MkDocs Material Theme for ASF
Author-email: ASF APD/Tools Team <uaf-asf-apd@alaska.edu>
License: BSD-3-Clause
Project-URL: Homepage, https://github.com/ASFHyP3/mkdocs-asf-theme
Project-URL: Bug Tracker, https://github.com/ASFHyP3/mkdocs-asf-theme/issues
Classifier: Intended Audience :: Science/Research
Classifier: License :: OSI Approved :: BSD License
Classifier: Natural Language :: English
Classifier: Operating System :: OS Independent
Classifier: Programming Language :: Python :: 3
Classifier: Programming Language :: Python :: 3.10
Classifier: Programming Language :: Python :: 3.11
Classifier: Programming Language :: Python :: 3.12
Requires-Python: >=3.10
License-File: LICENSE
Requires-Dist: mkdocs
Requires-Dist: mkdocs-material <10,>=9.4.2
